scriptor/__init__.py
scriptor/_version.py
scriptor/process.py
scriptor/program.py
scriptor/runner.py
scriptor/utils.py
scriptor/builtin/__init__.py
scriptor/builtin/python.py
scriptor/tests/__init__.py
scriptor/tests/test_runner.py
scriptor/tests/program/__init__.py
scriptor/tests/program/test_async.py
scriptor/tests/program/test_class.py
scriptor/tests/program/test_construct.py
scriptor/tests/program/test_run.py
scriptor/tests/program/test_start.py
scriptor-0.2.0.dist-info/LICENSE
scriptor-0.2.0.dist-info/METADATA
scriptor-0.2.0.dist-info/WHEEL
scriptor-0.2.0.dist-info/top_level.txt
scriptor-0.2.0.dist-info/RECORD
