Metadata-Version: 2.1
Name: scriptor
Version: 0.2.0
Summary: High-level command-line abstraction
Home-page: https://github.com/Miksus/scriptor.git
Author: Mikael Koli
Author-email: koli.mikael@gmail.com
Classifier: Development Status :: 4 - Beta
Classifier: Topic :: Communications :: Email
Classifier: Operating System :: OS Independent
Classifier: License :: OSI Approved :: MIT License
Classifier: Programming Language :: Python :: 3
Classifier: Programming Language :: Python :: 3.7
Classifier: Programming Language :: Python :: 3.8
Classifier: Programming Language :: Python :: 3.9
Classifier: Programming Language :: Python :: 3.10
Classifier: Intended Audience :: Developers
Requires-Python: >=3.7.0
License-File: LICENSE
